rabbitmq_decorator/__init__.py
rabbitmq_decorator/_common.py
rabbitmq_decorator/_logger.py
rabbitmq_decorator/exceptions.py
rabbitmq_decorator/rabbitmq_consumer.py
rabbitmq_decorator/rabbitmq_handler.py
rabbitmq_decorator/rabbitmq_producer.py
rabbitmq_decorator/connection/__init__.py
rabbitmq_decorator/connection/async_rabbitmq_connection.py
rabbitmq_decorator/connection/base_connection.py
rabbitmq_decorator/connection/rabbitmq_connection.py
rabbitmq_decorator-0.0.1.dist-info/LICENSE
rabbitmq_decorator-0.0.1.dist-info/METADATA
rabbitmq_decorator-0.0.1.dist-info/WHEEL
rabbitmq_decorator-0.0.1.dist-info/top_level.txt
rabbitmq_decorator-0.0.1.dist-info/RECORD
