Metadata-Version: 2.1
Name: rabbitmq-decorator
Version: 0.0.1
Summary: Easily send and receive messages to and from RabbitMQ message broker
Home-page: https://github.com/eliorerz/rabbitmq-decorator
Author: Elior Erez
Author-email: elior123@gmail.com
License: MIT
Classifier: Development Status :: 3 - Alpha
Classifier: License :: OSI Approved :: MIT License
Classifier: Operating System :: OS Independent
Classifier: Programming Language :: Python
Classifier: Programming Language :: Python :: 3
Classifier: Programming Language :: Python :: 3.7
Classifier: Programming Language :: Python :: 3.8
Classifier: Programming Language :: Python :: 3.9
Classifier: Topic :: Software Development :: Build Tools
Classifier: Topic :: Software Development :: Testing
Requires-Python: >=3.7.0
License-File: LICENSE
Requires-Dist: pika (~=1.3.0)
Requires-Dist: setuptools (~=65.0.0)
